blaz.py
setup.py
version.py
blaz.egg-info/PKG-INFO
blaz.egg-info/SOURCES.txt
blaz.egg-info/dependency_links.txt
blaz.egg-info/requires.txt
blaz.egg-info/top_level.txt