Metadata-Version: 1.0
Name: blaz
Version: 0.0.22
Summary: Composable tasks inside docker containers
Home-page: https://github.com/amiorin/blaz
Author: Alberto Miorin
Author-email: alberto.miorin@gmail.com
License: MIT
Platform: UNKNOWN
